discord/ext/localization/__init__.py
discord/ext/localization/errors.py
discord/ext/localization/localization.py
discord_localization-1.1.4.dist-info/LICENSE
discord_localization-1.1.4.dist-info/METADATA
discord_localization-1.1.4.dist-info/WHEEL
discord_localization-1.1.4.dist-info/top_level.txt
discord_localization-1.1.4.dist-info/RECORD
