Metadata-Version: 2.1
Name: discord-localization
Version: 1.1.4
Summary: A discord.py extension for command localization.
Author: Pearoo
Author-email: <contact@pearoo.dev>
Project-URL: Source, https://github.com/rnxm/discord-localization
Keywords: discord.py,i18n,translation,localisation,localization
Classifier: Programming Language :: Python :: 3
Classifier: License :: OSI Approved :: MIT License
Classifier: Operating System :: OS Independent
License-File: LICENSE
Requires-Dist: discord.py
